{
	"id": 0,
	"name": "fc-remote-invoke",
	"kind": 0,
	"kindString": "Project",
	"flags": {},
	"originalName": "",
	"children": [
		{
			"id": 1,
			"name": "default",
			"kind": 128,
			"kindString": "Class",
			"flags": {},
			"children": [
				{
					"id": 2,
					"name": "constructor",
					"kind": 512,
					"kindString": "Constructor",
					"flags": {},
					"signatures": [
						{
							"id": 3,
							"name": "new default",
							"kind": 16384,
							"kindString": "Constructor signature",
							"flags": {},
							"type": {
								"type": "reference",
								"id": 1,
								"name": "default"
							}
						}
					]
				},
				{
					"id": 12,
					"name": "handlerInputs",
					"kind": 2048,
					"kindString": "Method",
					"flags": {
						"isPrivate": true
					},
					"sources": [
						{
							"fileName": "index.ts",
							"line": 46,
							"character": 29
						}
					],
					"signatures": [
						{
							"id": 13,
							"name": "handlerInputs",
							"kind": 4096,
							"kindString": "Call signature",
							"flags": {},
							"parameters": [
								{
									"id": 14,
									"name": "inputs",
									"kind": 32768,
									"kindString": "Parameter",
									"flags": {},
									"type": {
										"type": "reference",
										"name": "InputProps"
									}
								}
							],
							"type": {
								"type": "reference",
								"typeArguments": [
									{
										"type": "intrinsic",
										"name": "any"
									}
								],
								"name": "Promise"
							}
						}
					]
				},
				{
					"id": 4,
					"name": "invoke",
					"kind": 2048,
					"kindString": "Method",
					"flags": {},
					"sources": [
						{
							"fileName": "index.ts",
							"line": 16,
							"character": 14
						}
					],
					"signatures": [
						{
							"id": 5,
							"name": "invoke",
							"kind": 4096,
							"kindString": "Call signature",
							"flags": {},
							"comment": {
								"shortText": "event 函数本地调试",
								"returns": "\n"
							},
							"parameters": [
								{
									"id": 6,
									"name": "inputs",
									"kind": 32768,
									"kindString": "Parameter",
									"flags": {},
									"comment": {},
									"type": {
										"type": "reference",
										"name": "InputProps"
									}
								}
							],
							"type": {
								"type": "reference",
								"typeArguments": [
									{
										"type": "intrinsic",
										"name": "any"
									}
								],
								"name": "Promise"
							}
						}
					]
				},
				{
					"id": 7,
					"name": "report",
					"kind": 2048,
					"kindString": "Method",
					"flags": {
						"isPrivate": true
					},
					"sources": [
						{
							"fileName": "index.ts",
							"line": 39,
							"character": 22
						}
					],
					"signatures": [
						{
							"id": 8,
							"name": "report",
							"kind": 4096,
							"kindString": "Call signature",
							"flags": {},
							"parameters": [
								{
									"id": 9,
									"name": "componentName",
									"kind": 32768,
									"kindString": "Parameter",
									"flags": {},
									"type": {
										"type": "intrinsic",
										"name": "string"
									}
								},
								{
									"id": 10,
									"name": "command",
									"kind": 32768,
									"kindString": "Parameter",
									"flags": {},
									"type": {
										"type": "intrinsic",
										"name": "string"
									}
								},
								{
									"id": 11,
									"name": "accountID",
									"kind": 32768,
									"kindString": "Parameter",
									"flags": {},
									"type": {
										"type": "intrinsic",
										"name": "string"
									}
								}
							],
							"type": {
								"type": "reference",
								"typeArguments": [
									{
										"type": "intrinsic",
										"name": "void"
									}
								],
								"name": "Promise"
							}
						}
					]
				}
			],
			"groups": [
				{
					"title": "Constructors",
					"kind": 512,
					"children": [
						2
					]
				},
				{
					"title": "Methods",
					"kind": 2048,
					"children": [
						12,
						4,
						7
					]
				}
			],
			"sources": [
				{
					"fileName": "index.ts",
					"line": 10,
					"character": 35
				}
			]
		}
	],
	"groups": [
		{
			"title": "Classes",
			"kind": 128,
			"children": [
				1
			]
		}
	],
	"sources": [
		{
			"fileName": "index.ts",
			"line": 1,
			"character": 0
		}
	]
}